README.rst
setup.py
paranoid/__init__.py
paranoid/flask.py
paranoid/models.py
paranoid/tests.py
sqla_paranoid.egg-info/PKG-INFO
sqla_paranoid.egg-info/SOURCES.txt
sqla_paranoid.egg-info/dependency_links.txt
sqla_paranoid.egg-info/not-zip-safe
sqla_paranoid.egg-info/requires.txt
sqla_paranoid.egg-info/top_level.txt