Metadata-Version: 1.0
Name: sqla-paranoid
Version: 0.1.0
Summary: Brings transparent soft delete to SQLAlchemy ORM
Home-page: UNKNOWN
Author: jean-philippe serafin
Author-email: serafinjp@gmail.com
License: MIT
Platform: UNKNOWN
